katsu/__init__.py
katsu/katsu_math.py
katsu/motion.py
katsu/mueller.py
katsu/polarimetry.py
katsu-0.1.0.dist-info/LICENSE.md
katsu-0.1.0.dist-info/METADATA
katsu-0.1.0.dist-info/WHEEL
katsu-0.1.0.dist-info/top_level.txt
katsu-0.1.0.dist-info/zip-safe
katsu-0.1.0.dist-info/RECORD
