Metadata-Version: 2.1
Name: katsu
Version: 0.1.0
Summary: Mueller calculus, polarimetry, and motion control
Author: Jaren N. Ashcraft
Author-email: "Jaren N. Ashcraft" <jashcraft@arizona.edu>
License: The MIT License (MIT)
Project-URL: GitHub, https://github.com/jashcraf/katsu
Project-URL: Documentation, https://katsu.readthedocs.org
Keywords: python,optics,telescope,polarization,mueller,polarimetry
Platform: any
Classifier: Programming Language :: Python :: 3
Classifier: Operating System :: OS Independent
Requires-Python: >=3.8
License-File: LICENSE.md
Requires-Dist: numpy
Requires-Dist: scipy
Requires-Dist: pyserial
